python_plot_mcp/__init__.py
python_plot_mcp/__main__.py
python_plot_mcp/server.py
python_plot_mcp-1.0.3.dist-info/licenses/LICENSE
python_plot_mcp-1.0.3.dist-info/METADATA
python_plot_mcp-1.0.3.dist-info/WHEEL
python_plot_mcp-1.0.3.dist-info/entry_points.txt
python_plot_mcp-1.0.3.dist-info/top_level.txt
python_plot_mcp-1.0.3.dist-info/RECORD
