Metadata-Version: 2.4
Name: python-plot-mcp
Version: 1.0.3
Summary: Python sandbox MCP server for matplotlib visualization
Author: qwe1453098533
License-Expression: MIT
Project-URL: Homepage, https://github.com/qwe1453098533/python-plot-mcp
Project-URL: Repository, https://github.com/qwe1453098533/python-plot-mcp
Project-URL: Issues, https://github.com/qwe1453098533/python-plot-mcp/issues
Keywords: mcp,model-context-protocol,python,matplotlib,visualization,plot,chart,sandbox
Classifier: Development Status :: 4 - Beta
Classifier: Intended Audience :: Developers
Classifier: Programming Language :: Python :: 3
Classifier: Programming Language :: Python :: 3.9
Classifier: Programming Language :: Python :: 3.10
Classifier: Programming Language :: Python :: 3.11
Classifier: Programming Language :: Python :: 3.12
Classifier: Topic :: Scientific/Engineering :: Visualization
Requires-Python: >=3.9
License-File: LICENSE
Requires-Dist: mcp>=1.1.3
Requires-Dist: matplotlib>=3.7.0
Requires-Dist: numpy>=1.24.0
Requires-Dist: Pillow>=10.0.0
Provides-Extra: dev
Requires-Dist: pytest; extra == "dev"
Requires-Dist: black; extra == "dev"
Requires-Dist: ruff; extra == "dev"
Dynamic: license-file
